mcmcAllotter/__init__.py
mcmcAllotter/mcmcAllotter.py
mcmcAllotter-0.1.0.dist-info/METADATA
mcmcAllotter-0.1.0.dist-info/WHEEL
mcmcAllotter-0.1.0.dist-info/top_level.txt
mcmcAllotter-0.1.0.dist-info/RECORD
