Metadata-Version: 2.1
Name: mcmcAllotter
Version: 0.1.0
Summary: Solve allottment/matching problems with MCMC
Home-page: https://github.com/saurabhkm/mcmcAllotter
Author: Saurabh Kumar
Author-email: saurabhkm@hotmail.com
License: UNKNOWN
Keywords: matching,allottment,mcmc,markovChainMonteCarlo,graphMatching
Platform: UNKNOWN
Classifier: Programming Language :: Python :: 2
Classifier: License :: OSI Approved :: MIT License
Classifier: Operating System :: OS Independent
Classifier: Development Status :: 5 - Production/Stable
Classifier: Natural Language :: English
Classifier: Intended Audience :: Education
Classifier: Operating System :: OS Independent
Classifier: Topic :: Software Development :: Libraries :: Python Modules
Requires-Dist: numpy
Requires-Dist: pandas
